mux_21/mux_21.v
`timescale 1ns / 1ps
module mux_21(a,b,c,y);
input a,b,c;
output y;
or (y,y1,y2);
and (y1,c1,a);
and (y2,c,b);
not (c1,c);
endmodule

mux_21/mux_21_test.v
`timescale 1ns / 1ps

module mux_21_test;

	// Inputs
	reg a;
	reg b;
	reg c;

	// Outputs
	wire y;

	// Instantiate the Unit Under Test (UUT)
	mux_21 uut (
		.a(a), 
		.b(b), 
		.c(c), 
		.y(y)
	);

	initial begin
		$dumpfile("mux_21_test.vcd");
     	$dumpvars(0,mux_21_test);
		// Initialize Inputs
		a = 1'b0;
		b = 1'b0;
		c = 1'b0;

		// Wait 100 ns for global reset to finish
		#100 $finish;
		end
		
		always #25 c=~c;
		always #10 b=~b;
		always #5 a=~a;
        
		// Add stimulus here
	always @(y)
    $display( "time =%0t \t c=%b b=%b a=%b \t output value y  =%b",$time,c,b,a,y);
      
endmodule

mux_21/mux_21_test.vcd
$date
	Sun Jan 17 16:51:01 2021
$end
$version
	Icarus Verilog
$end
$timescale
	1ps
$end
$scope module mux_21_test $end
$var wire 1 ! y $end
$var reg 1 " a $end
$var reg 1 # b $end
$var reg 1 $ c $end
$scope module uut $end
$var wire 1 " a $end
$var wire 1 # b $end
$var wire 1 $ c $end
$var wire 1 % c1 $end
$var wire 1 ! y $end
$var wire 1 & y1 $end
$var wire 1 ' y2 $end
$upscope $end
$upscope $end
$enddefinitions $end
#0
$dumpvars
0'
0&
1%
0$
0#
0"
0!
$end
#5000
1!
1&
1"
#10000
0!
0&
0"
1#
#15000
1!
1&
1"
#20000
0!
0&
0"
0#
#25000
0%
1"
1$
#30000
1!
1'
0"
1#
#35000
1"
#40000
0!
0'
0"
0#
#45000
1"
#50000
1%
0"
1#
0$
#55000
1!
1&
1"
#60000
0!
0&
0"
0#
#65000
1!
1&
1"
#70000
0!
0&
0"
1#
#75000
1!
1'
0%
1"
1$
#80000
0!
0'
0"
0#
#85000
1"
#90000
1!
1'
0"
1#
#95000
1"
#100000
0!
0'
1%
0"
0#
0$
